{
  "sections": {
    "banner": {
      "type": "banner",
      "settings": {
        "image": "shopify:\/\/shop_images\/BLOG-COVER-WITH-THREE-FRIENDS-LOOKING-AT-COMPUTER_edd14266-0f7c-4aa6-ba68-9d830bde59ca.jpg",
        "image_darken": false,
        "subtitle": "",
        "width": "wide",
        "banner_height": "medium",
        "padding_top": 0,
        "padding_bottom": 0,
        "css_class": "",
        "custom_css": "h1 {\ncolor: #FFFFFF;\ntext-shadow: 3px 3px  5px#000000;\ndisplay: none;\n}"
      }
    },
    "main": {
      "type": "blog__main",
      "settings": {
        "blog_tags": false,
        "blog_posts_per_row": 2,
        "blog_posts_per_page": 10,
        "pagination_type": "infinite_scroll",
        "show_sidebar": false,
        "sidebar_position": "left",
        "blog_author": true,
        "blog_date": true,
        "read_time": false,
        "blog_comment_count": false,
        "blog_show_tags": false,
        "blog_show_excerpt": true,
        "show_border": false,
        "button_label": "Read more",
        "button_type": "button--secondary",
        "width": "standard",
        "padding_top": 40,
        "padding_bottom": 40,
        "animation": "none",
        "css_class": "",
        "custom_css": ".pagination a {\n  border-radius: 100px;\n}\n.button {\n  border-radius: 100px;\n}"
      }
    }
  },
  "order": [
    "banner",
    "main"
  ]
}
